phg/__init__.py
phg/phg_to_shader.py
phg/pipe_string_phg.py
phg/shader_render.py
phg/visphg.py
phg/vis/GCU.dll
phg/vis/dragpad.exe
phg/vis/dragpad_config.ini
phg/vis/freeglut.dll
phg/vis/lua.dll
phg/vis/pycoder.exe
phg/vis/script.phg
phg/vis/sqlite3.dll
phg/vis/vis.exe
phg/vis/vis.ini
phg/vis/zlib1.dll
phg/vis/imgui/main.lua
phg_vis-1.3.2.dist-info/LICENSE
phg_vis-1.3.2.dist-info/METADATA
phg_vis-1.3.2.dist-info/WHEEL
phg_vis-1.3.2.dist-info/top_level.txt
phg_vis-1.3.2.dist-info/RECORD
