Metadata-Version: 2.1
Name: phg_vis
Version: 1.3.2
Summary: A package for the PHG modeling language and 3D visualization tool.
Home-page: https://github.com/panguojun/Coordinate-System
Author: romeosoft
Author-email: 18858146@qq.com
Platform: Windows
Classifier: Programming Language :: Python :: 3
Classifier: License :: OSI Approved :: MIT License
Classifier: Operating System :: Microsoft :: Windows
Requires-Python: >=3.8
License-File: LICENSE
